LICENSE.txt
README.md
setup.cfg
setup.py
src/pci/__init__.py
src/pci/__main__.py
src/pci/rem.py
src/pixel_console_image.egg-info/PKG-INFO
src/pixel_console_image.egg-info/SOURCES.txt
src/pixel_console_image.egg-info/dependency_links.txt
src/pixel_console_image.egg-info/entry_points.txt
src/pixel_console_image.egg-info/requires.txt
src/pixel_console_image.egg-info/top_level.txt
test/test.py