Metadata-Version: 2.1
Name: pixel-console-image
Version: 1.0.4
Summary: A simple image renderer & editor for the terminal using the .pci filetype
Home-page: https://github.com/El1teWatermelonGames/pci
Author: Elite Watermelon
Author-email: elitewatermelongames@gmail.com
License: Apache 2.0
Keywords: pci,rem,pci rem
Platform: UNKNOWN
License-File: LICENSE.txt
